pyroll/freiberg_flow_stress/__init__.py
pyroll/freiberg_flow_stress/freiberg_flow_stress.py
pyroll/freiberg_flow_stress/materials.py
pyroll/freiberg_flow_stress/report.py
pyroll_freiberg_flow_stress-3.0.1.post1.dist-info/METADATA
pyroll_freiberg_flow_stress-3.0.1.post1.dist-info/WHEEL
pyroll_freiberg_flow_stress-3.0.1.post1.dist-info/licenses/LICENSE
pyroll_freiberg_flow_stress-3.0.1.post1.dist-info/RECORD
